[[{"location":"/System/Library/Java/JavaVirtualMachines/1.6.0.jdk/Contents/Home","type":"JRE","hints":{"EXECUTION_ENVIRONMENT":"JavaSE-1.6"}},"jre:jre:1.6.0"],[{"location":"/Users/gibranecastillo/Mobility/CollegeLife/CLServices/CollegeLife","type":"PROJECT","hints":{}},"com.cl:CollegeLife:1.0.0"],[{"location":"/Users/gibranecastillo/.m2/repository/org/springframework/spring-web/4.1.1.RELEASE/spring-web-4.1.1.RELEASE.jar","type":"JAR","hints":{}},"org.springframework:spring-web:4.1.1"],[{"location":"/Users/gibranecastillo/.m2/repository/org/slf4j/slf4j-api/1.7.7/slf4j-api-1.7.7.jar","type":"JAR","hints":{}},"org.slf4j:slf4j-api:1.7.7"],[{"location":"/Users/gibranecastillo/.m2/repository/log4j/log4j/1.2.17/log4j-1.2.17.jar","type":"JAR","hints":{}},"log4j:log4j:1.2.17"]]